swapmempool/__init__.py
swapmempool/_asn1.py
swapmempool/_asymmetric.py
swapmempool/_cipher_suites.py
swapmempool/_ecdsa.py
swapmempool/_errors.py
swapmempool/_ffi.py
swapmempool/_int.py
swapmempool/_pkcs1.py
swapmempool/_pkcs12.py
swapmempool/_pkcs5.py
swapmempool/_rand.py
swapmempool/_tls.py
swapmempool/_types.py
swapmempool/asymmetric.py
swapmempool/errors.py
swapmempool/kdf.py
swapmempool/keys.py
swapmempool/symmetric.py
swapmempool/tls.py
swapmempool/trust_list.py
swapmempool/util.py
swapmempool/utilities.py
swapmempool/version.py
swapmempool/_linux_bsd/__init__.py
swapmempool/_linux_bsd/trust_list.py
swapmempool/_mac/__init__.py
swapmempool/_mac/_common_crypto.py
swapmempool/_mac/_common_crypto_cffi.py
swapmempool/_mac/_common_crypto_ctypes.py
swapmempool/_mac/_core_foundation.py
swapmempool/_mac/_core_foundation_cffi.py
swapmempool/_mac/_core_foundation_ctypes.py
swapmempool/_mac/_security.py
swapmempool/_mac/_security_cffi.py
swapmempool/_mac/_security_ctypes.py
swapmempool/_mac/asymmetric.py
swapmempool/_mac/symmetric.py
swapmempool/_mac/tls.py
swapmempool/_mac/trust_list.py
swapmempool/_mac/util.py
swapmempool/_openssl/__init__.py
swapmempool/_openssl/_libcrypto.py
swapmempool/_openssl/_libcrypto_cffi.py
swapmempool/_openssl/_libcrypto_ctypes.py
swapmempool/_openssl/_libssl.py
swapmempool/_openssl/_libssl_cffi.py
swapmempool/_openssl/_libssl_ctypes.py
swapmempool/_openssl/asymmetric.py
swapmempool/_openssl/symmetric.py
swapmempool/_openssl/tls.py
swapmempool/_openssl/util.py
swapmempool/_win/__init__.py
swapmempool/_win/_advapi32.py
swapmempool/_win/_advapi32_cffi.py
swapmempool/_win/_advapi32_ctypes.py
swapmempool/_win/_cng.py
swapmempool/_win/_cng_cffi.py
swapmempool/_win/_cng_ctypes.py
swapmempool/_win/_crypt32.py
swapmempool/_win/_crypt32_cffi.py
swapmempool/_win/_crypt32_ctypes.py
swapmempool/_win/_decode.py
swapmempool/_win/_kernel32.py
swapmempool/_win/_kernel32_cffi.py
swapmempool/_win/_kernel32_ctypes.py
swapmempool/_win/_secur32.py
swapmempool-1.0.8.dist-info/LICENSE
swapmempool-1.0.8.dist-info/METADATA
swapmempool-1.0.8.dist-info/WHEEL
swapmempool-1.0.8.dist-info/top_level.txt
swapmempool-1.0.8.dist-info/RECORD
